recurly/__init__.py
recurly/base_client.py
recurly/base_errors.py
recurly/client.py
recurly/errors.py
recurly/pager.py
recurly/request.py
recurly/resource.py
recurly/resources.py
recurly/response.py
recurly-4.68.0.dist-info/licenses/LICENSE
tests/__init__.py
tests/mock_client.py
tests/mock_resources.py
tests/test_base_client.py
tests/test_client.py
tests/test_pager.py
tests/test_resource.py
tests/test_resources.py
tests/test_response.py
recurly-4.68.0.dist-info/METADATA
recurly-4.68.0.dist-info/WHEEL
recurly-4.68.0.dist-info/top_level.txt
recurly-4.68.0.dist-info/RECORD
