Metadata-Version: 2.4
Name: recurly
Version: 4.68.0
Summary: Recurly v4
Home-page: https://github.com/recurly/recurly-client-python
Author: Developer Experience
Author-email: dx@recurly.com
License-File: LICENSE
Provides-Extra: test
Requires-Dist: coverage; extra == "test"
Dynamic: author
Dynamic: author-email
Dynamic: description
Dynamic: description-content-type
Dynamic: home-page
Dynamic: license-file
Dynamic: provides-extra
Dynamic: summary
